{
  "Id": "07df4018-9725-4c89-8490-5907447d668d",
  "Name": "LeaveRequest",
  "OriginalName": "LeaveRequest",
  "NamePlural": "LeaveRequests",
  "DatabaseTableName": "LeaveRequests",
  "Namespace": "LeaveRequests",
  "Type": 1,
  "MasterEntityName": null,
  "MasterEntity": null,
  "BaseClass": "FullAuditedAggregateRoot",
  "PageTitle": "LeaveRequests",
  "MenuIcon": "file-alt",
  "PrimaryKeyType": "Guid",
  "PreserveCustomCode": true,
  "IsMultiTenant": false,
  "CheckConcurrency": true,
  "BulkDeleteEnabled": true,
  "ShouldCreateUserInterface": true,
  "ShouldCreateBackend": true,
  "ShouldExportExcel": true,
  "ShouldAddMigration": true,
  "ShouldUpdateDatabase": true,
  "CreateTests": true,
  "Properties": [
    {
      "Id": "8d22fa42-50cf-4860-a173-0be110e93698",
      "Name": "LeaveRequestType",
      "Type": "enum",
      "EnumType": "LeaveRequestType",
      "EnumNamespace": "HRManagement",
      "EnumAngularImport": "shared/enums/leave-request-type",
      "EnumFilePath": "/src/HRManagement.Domain.Shared/LeaveRequestType.cs",
      "DefaultValue": null,
      "IsNullable": false,
      "IsRequired": false,
      "IsFilterable": true,
      "AllowEmptyStrings": false,
      "IsTextArea": false,
      "MinLength": null,
      "MaxLength": null,
      "SortOrder": 0,
      "SortType": 0,
      "Regex": "",
      "EmailValidation": false,
      "ShowOnList": true,
      "ShowOnCreateModal": true,
      "ShowOnEditModal": true,
      "ReadonlyOnEditModal": false,
      "EnumValues": {
        "SickLeave": 0,
        "CasualLeave": 1,
        "AnnualLeave": 2,
        "MaternityLeave": 3,
        "UnpaidLeave": 4,
        "Other": 5
      },
      "IsSelected": true,
      "MaxFileSize": null,
      "OrdinalIndex": 0
    },
    {
      "Id": "1b0cd505-d966-47d9-aefa-b7fc0d9a6085",
      "Name": "StartDate",
      "Type": "DateTime",
      "EnumType": "",
      "EnumNamespace": "",
      "EnumAngularImport": "shared/enums",
      "EnumFilePath": null,
      "DefaultValue": null,
      "IsNullable": false,
      "IsRequired": false,
      "IsFilterable": true,
      "AllowEmptyStrings": false,
      "IsTextArea": false,
      "MinLength": null,
      "MaxLength": null,
      "SortOrder": 0,
      "SortType": 0,
      "Regex": "",
      "EmailValidation": false,
      "ShowOnList": true,
      "ShowOnCreateModal": true,
      "ShowOnEditModal": true,
      "ReadonlyOnEditModal": false,
      "EnumValues": null,
      "IsSelected": true,
      "MaxFileSize": null,
      "OrdinalIndex": 0
    },
    {
      "Id": "534e9b5d-3336-4336-be62-d023ae95f08f",
      "Name": "EndDate",
      "Type": "DateTime",
      "EnumType": "",
      "EnumNamespace": "",
      "EnumAngularImport": "shared/enums",
      "EnumFilePath": null,
      "DefaultValue": null,
      "IsNullable": false,
      "IsRequired": false,
      "IsFilterable": true,
      "AllowEmptyStrings": false,
      "IsTextArea": false,
      "MinLength": null,
      "MaxLength": null,
      "SortOrder": 0,
      "SortType": 0,
      "Regex": "",
      "EmailValidation": false,
      "ShowOnList": true,
      "ShowOnCreateModal": true,
      "ShowOnEditModal": true,
      "ReadonlyOnEditModal": false,
      "EnumValues": null,
      "IsSelected": true,
      "MaxFileSize": null,
      "OrdinalIndex": 0
    },
    {
      "Id": "988300bd-40ec-46e0-b7f0-73abec578fce",
      "Name": "LeaveRequestStatus",
      "Type": "enum",
      "EnumType": "LeaveRequestStatus",
      "EnumNamespace": "HRManagement",
      "EnumAngularImport": "shared/enums/leave-request-status",
      "EnumFilePath": "/src/HRManagement.Domain.Shared/LeaveRequestStatus.cs",
      "DefaultValue": null,
      "IsNullable": false,
      "IsRequired": false,
      "IsFilterable": true,
      "AllowEmptyStrings": false,
      "IsTextArea": false,
      "MinLength": null,
      "MaxLength": null,
      "SortOrder": 0,
      "SortType": 0,
      "Regex": "",
      "EmailValidation": false,
      "ShowOnList": true,
      "ShowOnCreateModal": true,
      "ShowOnEditModal": true,
      "ReadonlyOnEditModal": false,
      "EnumValues": {
        "Pending": 0,
        "Approved": 1,
        "Rejected": 2,
        "Cancelled": 3
      },
      "IsSelected": true,
      "MaxFileSize": null,
      "OrdinalIndex": 0
    },
    {
      "Id": "e5dec4a9-5e7a-487d-9969-b8b62eb19e1d",
      "Name": "RequestedOn",
      "Type": "DateTime",
      "EnumType": "",
      "EnumNamespace": "",
      "EnumAngularImport": "shared/enums",
      "EnumFilePath": null,
      "DefaultValue": null,
      "IsNullable": false,
      "IsRequired": false,
      "IsFilterable": true,
      "AllowEmptyStrings": false,
      "IsTextArea": false,
      "MinLength": null,
      "MaxLength": null,
      "SortOrder": 0,
      "SortType": 0,
      "Regex": "",
      "EmailValidation": false,
      "ShowOnList": true,
      "ShowOnCreateModal": true,
      "ShowOnEditModal": true,
      "ReadonlyOnEditModal": false,
      "EnumValues": null,
      "IsSelected": true,
      "MaxFileSize": null,
      "OrdinalIndex": 0
    },
    {
      "Id": "d231c80e-3dba-4eed-b0f9-274473fe6d2b",
      "Name": "ReviewedOn",
      "Type": "DateTime",
      "EnumType": "",
      "EnumNamespace": "",
      "EnumAngularImport": "shared/enums",
      "EnumFilePath": null,
      "DefaultValue": null,
      "IsNullable": true,
      "IsRequired": false,
      "IsFilterable": true,
      "AllowEmptyStrings": false,
      "IsTextArea": false,
      "MinLength": null,
      "MaxLength": null,
      "SortOrder": 0,
      "SortType": 0,
      "Regex": "",
      "EmailValidation": false,
      "ShowOnList": true,
      "ShowOnCreateModal": true,
      "ShowOnEditModal": true,
      "ReadonlyOnEditModal": false,
      "EnumValues": null,
      "IsSelected": true,
      "MaxFileSize": null,
      "OrdinalIndex": 0
    },
    {
      "Id": "5c28cf87-c5d5-4e3e-82bc-4a20e38bd408",
      "Name": "WorkflowInstanceId",
      "Type": "string",
      "EnumType": "",
      "EnumNamespace": "",
      "EnumAngularImport": "shared/enums",
      "EnumFilePath": null,
      "DefaultValue": null,
      "IsNullable": false,
      "IsRequired": false,
      "IsFilterable": true,
      "AllowEmptyStrings": false,
      "IsTextArea": false,
      "MinLength": 0,
      "MaxLength": 1000,
      "SortOrder": 0,
      "SortType": 0,
      "Regex": "",
      "EmailValidation": false,
      "ShowOnList": true,
      "ShowOnCreateModal": true,
      "ShowOnEditModal": true,
      "ReadonlyOnEditModal": false,
      "EnumValues": null,
      "IsSelected": true,
      "MaxFileSize": null,
      "OrdinalIndex": 0
    }
  ],
  "NavigationProperties": [
    {
      "EntityNameWithDuplicationNumber": "Employee",
      "EntitySetNameWithDuplicationNumber": "Employees",
      "ReferencePropertyName": "Employee",
      "UiPickType": "Dropdown",
      "IsRequired": true,
      "IncludeEntitiesFromModules": false,
      "FromAbpModule": false,
      "Name": "EmployeeId",
      "DisplayProperty": "EmployeeNumber",
      "Namespace": "HRManagement.Employees",
      "EntityName": "Employee",
      "EntitySetName": "Employees",
      "DtoNamespace": "HRManagement.Employees",
      "DtoEntityName": "EmployeeDto",
      "Type": "Guid",
      "IsFilterable": true
    },
    {
      "EntityNameWithDuplicationNumber": "ReviewedBy",
      "EntitySetNameWithDuplicationNumber": "Users",
      "ReferencePropertyName": "ReviewedBy",
      "UiPickType": "Dropdown",
      "IsRequired": false,
      "IncludeEntitiesFromModules": false,
      "FromAbpModule": true,
      "Name": "ReviewedBy",
      "DisplayProperty": "Name",
      "Namespace": "Volo.Abp.Identity",
      "EntityName": "IdentityUser",
      "EntitySetName": "Users",
      "DtoNamespace": "Volo.Abp.Identity",
      "DtoEntityName": "IdentityUserDto",
      "Type": "Guid",
      "IsFilterable": true
    }
  ],
  "NavigationConnections": [],
  "ChildEntities": [],
  "PhysicalFileName": "LeaveRequest.json"
}